{"id": 1282816566514667521, "conversation_id": "1282816566514667521", "created_at": "2020-07-14 01:17:57 CEST", "date": "2020-07-14", "time": "01:17:57", "timezone": "+0100", "user_id": 251788355, "username": "makintamie", "name": "Muhammadu Makintami™", "place": "", "tweet": "Muhammadu Buhari did not fail you. Your primary leaders failed you woefully. He has done his part, let Borno State and the entire Northeast organise a roundtable and address the issue from it's root.", "language": "en", "mentions": [], "urls": [], "photos": [], "replies_count": 2, "retweets_count": 0, "likes_count": 0, "hashtags": [], "cashtags": [], "link": "https://twitter.com/Makintamie/status/1282816566514667521", "retweet": false, "quote_url": "https://twitter.com/Idris_jnrr/status/1282811657417367553", "video": 0, "thumbnail": "", "near": "", "geo": "9.083333333,7.533333,20km", "source": "", "user_rt_id": "", "user_rt": "", "retweet_id": "", "reply_to": [], "retweet_date": "", "translate": "", "trans_src": "", "trans_dest": ""}
{"id": 1282800193793138688, "conversation_id": "1282744207191543808", "created_at": "2020-07-14 00:12:54 CEST", "date": "2020-07-14", "time": "00:12:54", "timezone": "+0100", "user_id": 2536468210, "username": "countattorney", "name": "Count Of Confidence Attorney’s", "place": "", "tweet": "@NekkaSmith It took Buhari 6 month to look for Makami and Magu to help him fight corruption", "language": "en", "mentions": [], "urls": [], "photos": [], "replies_count": 1, "retweets_count": 0, "likes_count": 1, "hashtags": [], "cashtags": [], "link": "https://twitter.com/CountAttorney/status/1282800193793138688", "retweet": false, "quote_url": "", "video": 0, "thumbnail": "", "near": "", "geo": "9.083333333,7.533333,20km", "source": "", "user_rt_id": "", "user_rt": "", "retweet_id": "", "reply_to": [{"screen_name": "NekkaSmith", "name": "President One.acre|-| Dadiyata Disappeared", "id": "275046734"}], "retweet_date": "", "translate": "", "trans_src": "", "trans_dest": ""}
{"id": 1282799963823648769, "conversation_id": "1282555784270946305", "created_at": "2020-07-14 00:11:59 CEST", "date": "2020-07-14", "time": "00:11:59", "timezone": "+0100", "user_id": 2536468210, "username": "countattorney", "name": "Count Of Confidence Attorney’s", "place": "", "tweet": "@ShehuSani It took Buhari 6 month to look for Malami and Magu to help him fight corruption. Lol", "language": "en", "mentions": [], "urls": [], "photos": [], "replies_count": 0, "retweets_count": 0, "likes_count": 0, "hashtags": [], "cashtags": [], "link": "https://twitter.com/CountAttorney/status/1282799963823648769", "retweet": false, "quote_url": "", "video": 0, "thumbnail": "", "near": "", "geo": "9.083333333,7.533333,20km", "source": "", "user_rt_id": "", "user_rt": "", "retweet_id": "", "reply_to": [{"screen_name": "ShehuSani", "name": "Senator Shehu Sani", "id": "117042662"}], "retweet_date": "", "translate": "", "trans_src": "", "trans_dest": ""}
{"id": 1282784823615074304, "conversation_id": "1282784823615074304", "created_at": "2020-07-13 23:11:49 CEST", "date": "2020-07-13", "time": "23:11:49", "timezone": "+0100", "user_id": 1030843964692279297, "username": "krisjay04", "name": "kris", "place": "", "tweet": "Even with the help of the Ref still 5th norm no fit senior 3rd born not in buhari’s regime", "language": "en", "mentions": [], "urls": [], "photos": [], "replies_count": 0, "retweets_count": 0, "likes_count": 0, "hashtags": [], "cashtags": [], "link": "https://twitter.com/krisjay04/status/1282784823615074304", "retweet": false, "quote_url": "https://twitter.com/NenyeChelsea/status/1282783828134813697", "video": 0, "thumbnail": "", "near": "", "geo": "9.083333333,7.533333,20km", "source": "", "user_rt_id": "", "user_rt": "", "retweet_id": "", "reply_to": [], "retweet_date": "", "translate": "", "trans_src": "", "trans_dest": ""}
{"id": 1282716216465989635, "conversation_id": "1282716216465989635", "created_at": "2020-07-13 18:39:12 CEST", "date": "2020-07-13", "time": "18:39:12", "timezone": "+0100", "user_id": 2939509486, "username": "daminaboeric", "name": "Buhari's Sister🇳🇬", "place": "", "tweet": "Shame on Niger Delta people.  While y'all are fighting the forensic audit to hide your loots.  The Northern Development Commission is up and running.  Tomorrow they'll blame Buhari and Tinubu.", "language": "en", "mentions": [], "urls": [], "photos": [], "replies_count": 3, "retweets_count": 35, "likes_count": 72, "hashtags": [], "cashtags": [], "link": "https://twitter.com/DaminaboEric/status/1282716216465989635", "retweet": false, "quote_url": "", "video": 0, "thumbnail": "", "near": "", "geo": "9.083333333,7.533333,20km", "source": "", "user_rt_id": "", "user_rt": "", "retweet_id": "", "reply_to": [], "retweet_date": "", "translate": "", "trans_src": "", "trans_dest": ""}
{"id": 1282700257432928258, "conversation_id": "1282700257432928258", "created_at": "2020-07-13 17:35:47 CEST", "date": "2020-07-13", "time": "17:35:47", "timezone": "+0100", "user_id": 1131613353984561152, "username": "balexwali", "name": "bala wali", "place": "", "tweet": "They have succeeded in bringing down baba buhari. APC 🙆‍♂️🙆‍♂️", "language": "en", "mentions": [], "urls": [], "photos": [], "replies_count": 0, "retweets_count": 0, "likes_count": 2, "hashtags": [], "cashtags": [], "link": "https://twitter.com/balexwali/status/1282700257432928258", "retweet": false, "quote_url": "https://twitter.com/olayemi_123/status/1282600315016052742", "video": 0, "thumbnail": "", "near": "", "geo": "9.083333333,7.533333,20km", "source": "", "user_rt_id": "", "user_rt": "", "retweet_id": "", "reply_to": [], "retweet_date": "", "translate": "", "trans_src": "", "trans_dest": ""}
{"id": 1282697569672597507, "conversation_id": "1282697569672597507", "created_at": "2020-07-13 17:25:06 CEST", "date": "2020-07-13", "time": "17:25:06", "timezone": "+0100", "user_id": 2570774007, "username": "forever_rayyan", "name": "Chief Media🌍.", "place": "", "tweet": "The president of the United States of America Donald trump is wearing a mask, he is the number one citizen in the world, he is wearing a mask, he controls the sea and land activities, he is wearing a mask!! Why is Muhammadu Buhari not wearing a mask? Ok. #KeaDrive", "language": "en", "mentions": [], "urls": [], "photos": [], "replies_count": 1, "retweets_count": 0, "likes_count": 11, "hashtags": ["keadrive"], "cashtags": [], "link": "https://twitter.com/Forever_Rayyan/status/1282697569672597507", "retweet": false, "quote_url": "", "video": 0, "thumbnail": "", "near": "", "geo": "9.083333333,7.533333,20km", "source": "", "user_rt_id": "", "user_rt": "", "retweet_id": "", "reply_to": [], "retweet_date": "", "translate": "", "trans_src": "", "trans_dest": ""}
{"id": 1282693454468980737, "conversation_id": "1282562882421633025", "created_at": "2020-07-13 17:08:45 CEST", "date": "2020-07-13", "time": "17:08:45", "timezone": "+0100", "user_id": 964195904206114816, "username": "atanda_martins", "name": "Martins Atanda", "place": "", "tweet": "@vanguardngrnews Happy birthday! Good that you are alive to witness the government you campaigned for. Buhari and APC has done this much good to Nigeria. A track record indeed!!!", "language": "en", "mentions": [], "urls": [], "photos": [], "replies_count": 0, "retweets_count": 0, "likes_count": 0, "hashtags": [], "cashtags": [], "link": "https://twitter.com/atanda_martins/status/1282693454468980737", "retweet": false, "quote_url": "", "video": 0, "thumbnail": "", "near": "", "geo": "9.083333333,7.533333,20km", "source": "", "user_rt_id": "", "user_rt": "", "retweet_id": "", "reply_to": [{"screen_name": "vanguardngrnews", "name": "Vanguard Newspapers", "id": "39975533"}], "retweet_date": "", "translate": "", "trans_src": "", "trans_dest": ""}
{"id": 1282683844160892929, "conversation_id": "1282644962677592064", "created_at": "2020-07-13 16:30:34 CEST", "date": "2020-07-13", "time": "16:30:34", "timezone": "+0100", "user_id": 1543807460, "username": "chuka_60571", "name": "CHUKA ABATAGO✨", "place": "", "tweet": "@FBanks7 Wow.....can I believe he is talking to Buhari and his government", "language": "en", "mentions": [], "urls": [], "photos": [], "replies_count": 0, "retweets_count": 0, "likes_count": 0, "hashtags": [], "cashtags": [], "link": "https://twitter.com/chuka_60571/status/1282683844160892929", "retweet": false, "quote_url": "", "video": 0, "thumbnail": "", "near": "", "geo": "9.083333333,7.533333,20km", "source": "", "user_rt_id": "", "user_rt": "", "retweet_id": "", "reply_to": [{"screen_name": "FBanks7", "name": "Chief Ezekwueche 👑", "id": "599435932"}], "retweet_date": "", "translate": "", "trans_src": "", "trans_dest": ""}
{"id": 1282651846797135872, "conversation_id": "1282645172409577478", "created_at": "2020-07-13 14:23:25 CEST", "date": "2020-07-13", "time": "14:23:25", "timezone": "+0100", "user_id": 176076251, "username": "ladyoutshine", "name": "Tammy says end SARS", "place": "", "tweet": "@Slimeech That the Authors think Buhari was a popular candidate in 2003, 2007, and 2011 and the elections then was rigged against him is totally laughable to say the least!", "language": "en", "mentions": [], "urls": [], "photos": [], "replies_count": 0, "retweets_count": 0, "likes_count": 1, "hashtags": [], "cashtags": [], "link": "https://twitter.com/ladyoutshine/status/1282651846797135872", "retweet": false, "quote_url": "", "video": 0, "thumbnail": "", "near": "", "geo": "9.083333333,7.533333,20km", "source": "", "user_rt_id": "", "user_rt": "", "retweet_id": "", "reply_to": [{"screen_name": "slimeech", "name": "Mr. O.I Kolawole", "id": "215208974"}], "retweet_date": "", "translate": "", "trans_src": "", "trans_dest": ""}
{"id": 1282646628575457281, "conversation_id": "1282644183799521280", "created_at": "2020-07-13 14:02:41 CEST", "date": "2020-07-13", "time": "14:02:41", "timezone": "+0100", "user_id": 79536591, "username": "princemiracle22", "name": "Chinyelugo", "place": "", "tweet": "@cozzbie Well you supported Buhari, so i am not surprised", "language": "en", "mentions": [], "urls": [], "photos": [], "replies_count": 1, "retweets_count": 0, "likes_count": 0, "hashtags": [], "cashtags": [], "link": "https://twitter.com/PrinceMiracle22/status/1282646628575457281", "retweet": false, "quote_url": "", "video": 0, "thumbnail": "", "near": "", "geo": "9.083333333,7.533333,20km", "source": "", "user_rt_id": "", "user_rt": "", "retweet_id": "", "reply_to": [{"screen_name": "cozzbie", "name": "(0, eval)('yats')", "id": "60112188"}], "retweet_date": "", "translate": "", "trans_src": "", "trans_dest": ""}
{"id": 1282638763919839235, "conversation_id": "1282638763919839235", "created_at": "2020-07-13 13:31:26 CEST", "date": "2020-07-13", "time": "13:31:26", "timezone": "+0100", "user_id": 50317623, "username": "nlychildproblem", "name": "Ahmed Bin Dimples🪂", "place": "", "tweet": "Buhari sef fit be cake.", "language": "in", "mentions": [], "urls": [], "photos": [], "replies_count": 0, "retweets_count": 0, "likes_count": 0, "hashtags": [], "cashtags": [], "link": "https://twitter.com/nlychildproblem/status/1282638763919839235", "retweet": false, "quote_url": "", "video": 0, "thumbnail": "", "near": "", "geo": "9.083333333,7.533333,20km", "source": "", "user_rt_id": "", "user_rt": "", "retweet_id": "", "reply_to": [], "retweet_date": "", "translate": "", "trans_src": "", "trans_dest": ""}
{"id": 1282621889186234374, "conversation_id": "1282621889186234374", "created_at": "2020-07-13 12:24:23 CEST", "date": "2020-07-13", "time": "12:24:23", "timezone": "+0100", "user_id": 1323448856, "username": "thegist9ja", "name": "the_black_dorian_grey🧩", "place": "", "tweet": "The past few weeks have really shown that buhari isn’t ruling this country at all", "language": "en", "mentions": [], "urls": [], "photos": [], "replies_count": 0, "retweets_count": 0, "likes_count": 0, "hashtags": [], "cashtags": [], "link": "https://twitter.com/TheGist9ja/status/1282621889186234374", "retweet": false, "quote_url": "https://twitter.com/jacksonpbn/status/1282427575487340544", "video": 0, "thumbnail": "", "near": "", "geo": "9.083333333,7.533333,20km", "source": "", "user_rt_id": "", "user_rt": "", "retweet_id": "", "reply_to": [], "retweet_date": "", "translate": "", "trans_src": "", "trans_dest": ""}
{"id": 1282588094978564096, "conversation_id": "1282588094978564096", "created_at": "2020-07-13 10:10:05 CEST", "date": "2020-07-13", "time": "10:10:05", "timezone": "+0100", "user_id": 962039481460314112, "username": "urbanchowbyjae", "name": "jaè", "place": "", "tweet": "Piping hot stew made with beef and ponmo.  Even with the increase in the price of tomato 🍅 we still deliver maximum meals. We don’t compromise when it comes to the satisfaction of our customers.   One million boys | #wecantbreathe #Buhari  https://t.co/vYbBw3wiNp", "language": "en", "mentions": [], "urls": [], "photos": [], "replies_count": 0, "retweets_count": 1, "likes_count": 5, "hashtags": ["wecantbreathe", "buhari"], "cashtags": [], "link": "https://twitter.com/urbanchowbyjae/status/1282588094978564096", "retweet": false, "quote_url": "", "video": 1, "thumbnail": "https://pbs.twimg.com/ext_tw_video_thumb/1282587968104996864/pu/img/u1zptrIShrvLfhtb.jpg", "near": "", "geo": "9.083333333,7.533333,20km", "source": "", "user_rt_id": "", "user_rt": "", "retweet_id": "", "reply_to": [], "retweet_date": "", "translate": "", "trans_src": "", "trans_dest": ""}
{"id": 1282581534738964480, "conversation_id": "1282581534738964480", "created_at": "2020-07-13 09:44:01 CEST", "date": "2020-07-13", "time": "09:44:01", "timezone": "+0100", "user_id": 1128319202253791234, "username": "harryblinkzs", "name": "LM10 MESSI((Wizkid)) 🇳🇬", "place": "", "tweet": "@wizkidayo Never drop MadeinLagos, but E don already dey contest for Album of the Year!! 🐐  #channelstv #NicoleSeah #Buhari  https://t.co/p3317hwNaa", "language": "en", "mentions": [], "urls": [], "photos": ["https://pbs.twimg.com/media/EcylG1YXgAEhTI2.jpg"], "replies_count": 0, "retweets_count": 3, "likes_count": 3, "hashtags": ["channelstv", "nicoleseah", "buhari"], "cashtags": [], "link": "https://twitter.com/harryblinkzs/status/1282581534738964480", "retweet": false, "quote_url": "", "video": 1, "thumbnail": "https://pbs.twimg.com/media/EcylG1YXgAEhTI2.jpg", "near": "", "geo": "9.083333333,7.533333,20km", "source": "", "user_rt_id": "", "user_rt": "", "retweet_id": "", "reply_to": [], "retweet_date": "", "translate": "", "trans_src": "", "trans_dest": ""}
{"id": 1282559845762240512, "conversation_id": "1282415413247332359", "created_at": "2020-07-13 08:17:50 CEST", "date": "2020-07-13", "time": "08:17:50", "timezone": "+0100", "user_id": 365722591, "username": "tosinadex", "name": "EagleEye", "place": "", "tweet": "@InibeheEffiong All they do now is justify why they brought Buhari and took away GEJ", "language": "en", "mentions": [], "urls": [], "photos": [], "replies_count": 0, "retweets_count": 0, "likes_count": 0, "hashtags": [], "cashtags": [], "link": "https://twitter.com/tosinadex/status/1282559845762240512", "retweet": false, "quote_url": "", "video": 0, "thumbnail": "", "near": "", "geo": "9.083333333,7.533333,20km", "source": "", "user_rt_id": "", "user_rt": "", "retweet_id": "", "reply_to": [{"screen_name": "InibeheEffiong", "name": "Inibehe Effiong", "id": "507351120"}], "retweet_date": "", "translate": "", "trans_src": "", "trans_dest": ""}
{"id": 1282536190110052353, "conversation_id": "1282536190110052353", "created_at": "2020-07-13 06:43:50 CEST", "date": "2020-07-13", "time": "06:43:50", "timezone": "+0100", "user_id": 1282302617067061249, "username": "nadiafinds", "name": "made in nigeria #EndSARS", "place": "", "tweet": "this NDDC issue is proof that corruption is inherent in nigeria. are we finally going to stop pretending as if all our problems start and end with Buhari ?", "language": "en", "mentions": [], "urls": [], "photos": [], "replies_count": 0, "retweets_count": 0, "likes_count": 1, "hashtags": [], "cashtags": [], "link": "https://twitter.com/nadiafinds/status/1282536190110052353", "retweet": false, "quote_url": "", "video": 0, "thumbnail": "", "near": "", "geo": "9.083333333,7.533333,20km", "source": "", "user_rt_id": "", "user_rt": "", "retweet_id": "", "reply_to": [], "retweet_date": "", "translate": "", "trans_src": "", "trans_dest": ""}
