{"id": 1092859427672281088, "conversation_id": "1092859427672281088", "created_at": "2019-02-05 19:56:06 CET", "date": "2019-02-05", "time": "19:56:06", "timezone": "+0100", "user_id": 129293800, "username": "egbeprecious", "name": "Ama Lambeths", "place": {"type": "Point", "coordinates": [9.004467, 7.2705517]}, "tweet": "#Repost @saharareporters (get_repost) ・・・ Buhari Is A 'Liar', Says Foreign Policy Magazine _ President Muhammadu Buhari, currently seeking a return to power on the platform of the All…  https://t.co/90ipiCCbna", "language": "en", "mentions": [{"screen_name": "saharareporters", "name": "sahara reporters", "id": "17409452"}], "urls": ["https://www.instagram.com/p/BtgsydQAU04/?utm_source=ig_twitter_share&igshid=huax1chcs49v"], "photos": [], "replies_count": 0, "retweets_count": 0, "likes_count": 0, "hashtags": ["repost"], "cashtags": [], "link": "https://twitter.com/egbeprecious/status/1092859427672281088", "retweet": false, "quote_url": "", "video": 0, "thumbnail": "", "near": "", "geo": "9.083333333,7.533333,20km", "source": "", "user_rt_id": "", "user_rt": "", "retweet_id": "", "reply_to": [], "retweet_date": "", "translate": "", "trans_src": "", "trans_dest": ""}
{"id": 1092776303281922048, "conversation_id": "1092776303281922048", "created_at": "2019-02-05 14:25:48 CET", "date": "2019-02-05", "time": "14:25:48", "timezone": "+0100", "user_id": 3949655296, "username": "dungurawa1", "name": "Hassan Hussain", "place": {"type": "Point", "coordinates": [9.07633, 7.39378]}, "tweet": "Vote Baba BUHARI to Make use of your vote therefore, it wll not be Wested @ Life camp Gwarimpa Abuja  https://t.co/06ZYXIOlbr", "language": "en", "mentions": [], "urls": ["https://www.instagram.com/p/BtgG_UbHDFI/?utm_source=ig_twitter_share&igshid=1eq6h0zszhv91"], "photos": [], "replies_count": 0, "retweets_count": 0, "likes_count": 0, "hashtags": [], "cashtags": [], "link": "https://twitter.com/dungurawa1/status/1092776303281922048", "retweet": false, "quote_url": "", "video": 0, "thumbnail": "", "near": "", "geo": "9.083333333,7.533333,20km", "source": "", "user_rt_id": "", "user_rt": "", "retweet_id": "", "reply_to": [], "retweet_date": "", "translate": "", "trans_src": "", "trans_dest": ""}
{"id": 1092859427672281088, "conversation_id": "1092859427672281088", "created_at": "2019-02-05 19:56:06 CET", "date": "2019-02-05", "time": "19:56:06", "timezone": "+0100", "user_id": 129293800, "username": "egbeprecious", "name": "Ama Lambeths", "place": {"type": "Point", "coordinates": [9.004467, 7.2705517]}, "tweet": "#Repost @saharareporters (get_repost) ・・・ Buhari Is A 'Liar', Says Foreign Policy Magazine _ President Muhammadu Buhari, currently seeking a return to power on the platform of the All…  https://t.co/90ipiCCbna", "language": "en", "mentions": [{"screen_name": "saharareporters", "name": "sahara reporters", "id": "17409452"}], "urls": ["https://www.instagram.com/p/BtgsydQAU04/?utm_source=ig_twitter_share&igshid=huax1chcs49v"], "photos": [], "replies_count": 0, "retweets_count": 0, "likes_count": 0, "hashtags": ["repost"], "cashtags": [], "link": "https://twitter.com/egbeprecious/status/1092859427672281088", "retweet": false, "quote_url": "", "video": 0, "thumbnail": "", "near": "", "geo": "9.083333333,7.533333,20km", "source": "", "user_rt_id": "", "user_rt": "", "retweet_id": "", "reply_to": [], "retweet_date": "", "translate": "", "trans_src": "", "trans_dest": ""}
{"id": 1092776303281922048, "conversation_id": "1092776303281922048", "created_at": "2019-02-05 14:25:48 CET", "date": "2019-02-05", "time": "14:25:48", "timezone": "+0100", "user_id": 3949655296, "username": "dungurawa1", "name": "Hassan Hussain", "place": {"type": "Point", "coordinates": [9.07633, 7.39378]}, "tweet": "Vote Baba BUHARI to Make use of your vote therefore, it wll not be Wested @ Life camp Gwarimpa Abuja  https://t.co/06ZYXIOlbr", "language": "en", "mentions": [], "urls": ["https://www.instagram.com/p/BtgG_UbHDFI/?utm_source=ig_twitter_share&igshid=1eq6h0zszhv91"], "photos": [], "replies_count": 0, "retweets_count": 0, "likes_count": 0, "hashtags": [], "cashtags": [], "link": "https://twitter.com/dungurawa1/status/1092776303281922048", "retweet": false, "quote_url": "", "video": 0, "thumbnail": "", "near": "", "geo": "9.083333333,7.533333,20km", "source": "", "user_rt_id": "", "user_rt": "", "retweet_id": "", "reply_to": [], "retweet_date": "", "translate": "", "trans_src": "", "trans_dest": ""}
