{"id": 1314350092107874304, "conversation_id": "1314350092107874304", "created_at": "2020-10-09 01:40:56 CEST", "date": "2020-10-09", "time": "01:40:56", "timezone": "+0100", "user_id": 236556051, "username": "mrrebelxo", "name": "𝙼𝚛 𝚁𝚎𝚋𝚎𝚕", "place": "", "tweet": "If you can’t come out to protest, plis use the hashtags, tag them media houses esp the foreign ones, Buhari govt don’t like to be aired, let us all drag their filthy asses, we meet at force HQ tomorrow, Abuja tweeps come out let’s do this for our fallen brothers #EndSarsProtests", "language": "en", "mentions": [], "urls": [], "photos": [], "replies_count": 2, "retweets_count": 8, "likes_count": 12, "hashtags": ["endsarsprotests"], "cashtags": [], "link": "https://twitter.com/mrrebelxo/status/1314350092107874304", "retweet": false, "quote_url": "", "video": 0, "thumbnail": "", "near": "", "geo": "9.083333333,7.533333,20km", "source": "", "user_rt_id": "", "user_rt": "", "retweet_id": "", "reply_to": [], "retweet_date": "", "translate": "", "trans_src": "", "trans_dest": ""}
{"id": 1314342639823618048, "conversation_id": "1314342639823618048", "created_at": "2020-10-09 01:11:19 CEST", "date": "2020-10-09", "time": "01:11:19", "timezone": "+0100", "user_id": 170095031, "username": "marvincuche", "name": "hala: @marvin", "place": "", "tweet": "Why name this after Buhari?", "language": "en", "mentions": [], "urls": [], "photos": [], "replies_count": 0, "retweets_count": 0, "likes_count": 1, "hashtags": [], "cashtags": [], "link": "https://twitter.com/marvincuche/status/1314342639823618048", "retweet": false, "quote_url": "https://twitter.com/EbonyiGov/status/1314094251777634304", "video": 0, "thumbnail": "", "near": "", "geo": "9.083333333,7.533333,20km", "source": "", "user_rt_id": "", "user_rt": "", "retweet_id": "", "reply_to": [], "retweet_date": "", "translate": "", "trans_src": "", "trans_dest": ""}
{"id": 1314263725776478211, "conversation_id": "1314254766785138695", "created_at": "2020-10-08 19:57:44 CEST", "date": "2020-10-08", "time": "19:57:44", "timezone": "+0100", "user_id": 116264916, "username": "adnangawuna", "name": "Muhammad Hamma", "place": "", "tweet": "@adnan_buhari Off ur mic Isssokay", "language": "en", "mentions": [], "urls": [], "photos": [], "replies_count": 1, "retweets_count": 0, "likes_count": 1, "hashtags": [], "cashtags": [], "link": "https://twitter.com/AdnanGawuna/status/1314263725776478211", "retweet": false, "quote_url": "", "video": 0, "thumbnail": "", "near": "", "geo": "9.083333333,7.533333,20km", "source": "", "user_rt_id": "", "user_rt": "", "retweet_id": "", "reply_to": [{"screen_name": "adnan_buhari", "name": "Engr. Adnan", "id": "886385466"}], "retweet_date": "", "translate": "", "trans_src": "", "trans_dest": ""}
{"id": 1314253568648646657, "conversation_id": "1314253568648646657", "created_at": "2020-10-08 19:17:23 CEST", "date": "2020-10-08", "time": "19:17:23", "timezone": "+0100", "user_id": 89894744, "username": "usmanyusuf", "name": "usmanov", "place": "", "tweet": "*Nigeria Heading For Another Recession, To Recover In 2021 – Buhari*  _The President made the remarks during the presentation of the 2021 budget proposal to the National Assembly._  _*Like many other countries, the Nigerian economy has been hit hard by the  https://t.co/KMxaQbVpPn", "language": "en", "mentions": [], "urls": ["https://thenigerialawyer.com/nigeria-heading-for-another-recession-to-recover-in-2021-buhari/"], "photos": [], "replies_count": 0, "retweets_count": 0, "likes_count": 0, "hashtags": [], "cashtags": [], "link": "https://twitter.com/usmanyusuf/status/1314253568648646657", "retweet": false, "quote_url": "", "video": 0, "thumbnail": "", "near": "", "geo": "9.083333333,7.533333,20km", "source": "", "user_rt_id": "", "user_rt": "", "retweet_id": "", "reply_to": [], "retweet_date": "", "translate": "", "trans_src": "", "trans_dest": ""}
{"id": 1314245035152596994, "conversation_id": "1314218046664273921", "created_at": "2020-10-08 18:43:28 CEST", "date": "2020-10-08", "time": "18:43:28", "timezone": "+0100", "user_id": 1257903216089616386, "username": "ghostsk6", "name": "Abubakar Sadeeq", "place": "", "tweet": "@Onye_Nsogbu @SaharaReporters @MBuhari If you believe such things then u are still new in Nigeria. Is it not the same tinubu that is supporting Buhari?", "language": "en", "mentions": [], "urls": [], "photos": [], "replies_count": 1, "retweets_count": 0, "likes_count": 1, "hashtags": [], "cashtags": [], "link": "https://twitter.com/Ghostsk6/status/1314245035152596994", "retweet": false, "quote_url": "", "video": 0, "thumbnail": "", "near": "", "geo": "9.083333333,7.533333,20km", "source": "", "user_rt_id": "", "user_rt": "", "retweet_id": "", "reply_to": [{"screen_name": "Onye_Nsogbu", "name": "Mazi Onye_Nsogbu", "id": "1243979451303636992"}, {"screen_name": "SaharaReporters", "name": "Sahara Reporters", "id": "17409452"}, {"screen_name": "MBuhari", "name": "Muhammadu Buhari", "id": "2936714848"}], "retweet_date": "", "translate": "", "trans_src": "", "trans_dest": ""}
{"id": 1314216771537174530, "conversation_id": "1311202118494191616", "created_at": "2020-10-08 16:51:09 CEST", "date": "2020-10-08", "time": "16:51:09", "timezone": "+0100", "user_id": 2183039600, "username": "omo_iyayemi", "name": "yemi", "place": "", "tweet": "@Popsyno @Tutsy22 @MBuhari @burnaboy Is that what your father Bihari told you? That he had agreement with buhari ?", "language": "en", "mentions": [], "urls": [], "photos": [], "replies_count": 1, "retweets_count": 0, "likes_count": 1, "hashtags": [], "cashtags": [], "link": "https://twitter.com/Omo_Iyayemi/status/1314216771537174530", "retweet": false, "quote_url": "", "video": 0, "thumbnail": "", "near": "", "geo": "9.083333333,7.533333,20km", "source": "", "user_rt_id": "", "user_rt": "", "retweet_id": "", "reply_to": [{"screen_name": "Popsyno", "name": "Affidavit Doctor 🇳🇬", "id": "287237089"}, {"screen_name": "Tutsy22", "name": "Adetutu Balogun, MBA", "id": "498719623"}, {"screen_name": "MBuhari", "name": "Muhammadu Buhari", "id": "2936714848"}, {"screen_name": "burnaboy", "name": "Burna Boy", "id": "215052012"}], "retweet_date": "", "translate": "", "trans_src": "", "trans_dest": ""}
{"id": 1314215242042281993, "conversation_id": "1314215242042281993", "created_at": "2020-10-08 16:45:05 CEST", "date": "2020-10-08", "time": "16:45:05", "timezone": "+0100", "user_id": 1307272538846826497, "username": "wisedj", "name": "DJ WISE ON DECK", "place": "", "tweet": "We have not done fixing our problems and mr president Muhammadu  buhari is busy consoling somebody who don't have any business with he. AND SARS ARE KILLING US @#%$&amp;  https://t.co/qmmkUNMPNe", "language": "en", "mentions": [], "urls": [], "photos": ["https://pbs.twimg.com/media/Ej0HzAtWAAEnffc.jpg"], "replies_count": 0, "retweets_count": 0, "likes_count": 0, "hashtags": [], "cashtags": [], "link": "https://twitter.com/WiseDj/status/1314215242042281993", "retweet": false, "quote_url": "", "video": 1, "thumbnail": "https://pbs.twimg.com/media/Ej0HzAtWAAEnffc.jpg", "near": "", "geo": "9.083333333,7.533333,20km", "source": "", "user_rt_id": "", "user_rt": "", "retweet_id": "", "reply_to": [], "retweet_date": "", "translate": "", "trans_src": "", "trans_dest": ""}
{"id": 1314215234135977987, "conversation_id": "1311202118494191616", "created_at": "2020-10-08 16:45:03 CEST", "date": "2020-10-08", "time": "16:45:03", "timezone": "+0100", "user_id": 2183039600, "username": "omo_iyayemi", "name": "yemi", "place": "", "tweet": "@onwuemeneemman1 @AkinsanyaOwo1 @Tutsy22 @SodiqTade @MBuhari @YeleSowore So you are blaming Sowore for Buhari failure, drink water, you will be fine", "language": "en", "mentions": [], "urls": [], "photos": [], "replies_count": 0, "retweets_count": 0, "likes_count": 0, "hashtags": [], "cashtags": [], "link": "https://twitter.com/Omo_Iyayemi/status/1314215234135977987", "retweet": false, "quote_url": "", "video": 0, "thumbnail": "", "near": "", "geo": "9.083333333,7.533333,20km", "source": "", "user_rt_id": "", "user_rt": "", "retweet_id": "", "reply_to": [{"screen_name": "onwuemeneemman1", "name": "Uncle Emma", "id": "2159626397"}, {"screen_name": "AkinsanyaOwo1", "name": "A.O.B", "id": "939572723134672896"}, {"screen_name": "Tutsy22", "name": "Adetutu Balogun, MBA", "id": "498719623"}, {"screen_name": "SodiqTade", "name": "Premier", "id": "1032296549286666240"}, {"screen_name": "MBuhari", "name": "Muhammadu Buhari", "id": "2936714848"}, {"screen_name": "YeleSowore", "name": "Omoyele Sowore", "id": "1051795722"}], "retweet_date": "", "translate": "", "trans_src": "", "trans_dest": ""}
{"id": 1314205749489197062, "conversation_id": "1314205749489197062", "created_at": "2020-10-08 16:07:22 CEST", "date": "2020-10-08", "time": "16:07:22", "timezone": "+0100", "user_id": 2899302327, "username": "page36news", "name": "Page 36", "place": "", "tweet": "PHOTOS: President Muhammadu Buhari Presents The Draft Of The 2021 Appropriation Bill To The @nassnigeria, At The National Assembly Complex, Abuja, Today.   VISIT  https://t.co/XduqfBXXA6  #FGNBudget2021 #Budget2021  https://t.co/MwcdvDnLJ7", "language": "en", "mentions": [{"screen_name": "nassnigeria", "name": "national assembly", "id": "2845191549"}], "urls": ["http://page36news.com"], "photos": ["https://pbs.twimg.com/media/Ejz_HibVcAI8ug3.jpg", "https://pbs.twimg.com/media/Ejz_IMUU4AoHW8K.jpg", "https://pbs.twimg.com/media/Ejz_I5BVgAApL5r.jpg", "https://pbs.twimg.com/media/Ejz_JwoUYAkmEcd.jpg"], "replies_count": 0, "retweets_count": 10, "likes_count": 8, "hashtags": ["fgnbudget2021", "budget2021"], "cashtags": [], "link": "https://twitter.com/page36news/status/1314205749489197062", "retweet": false, "quote_url": "", "video": 1, "thumbnail": "https://pbs.twimg.com/media/Ejz_HibVcAI8ug3.jpg", "near": "", "geo": "9.083333333,7.533333,20km", "source": "", "user_rt_id": "", "user_rt": "", "retweet_id": "", "reply_to": [], "retweet_date": "", "translate": "", "trans_src": "", "trans_dest": ""}
{"id": 1314201560100921347, "conversation_id": "1314201560100921347", "created_at": "2020-10-08 15:50:43 CEST", "date": "2020-10-08", "time": "15:50:43", "timezone": "+0100", "user_id": 89894744, "username": "usmanyusuf", "name": "usmanov", "place": "", "tweet": "President Muhammadu Buhari presents 2021 Draft Appropriation Bill to National Assembly at the National Assembly Complex in Abuja on 8th Oct 2020, PHOTOS:📸Bayo Omoboriowo  https://t.co/sVZvlmRh6r", "language": "en", "mentions": [], "urls": [], "photos": ["https://pbs.twimg.com/media/Ejz7V-0UwAIx5gg.jpg", "https://pbs.twimg.com/media/Ejz7V-rVgAMzKC9.jpg", "https://pbs.twimg.com/media/Ejz7V-tU8AUvCZ8.jpg", "https://pbs.twimg.com/media/Ejz7V-sVkAImA3K.jpg"], "replies_count": 0, "retweets_count": 0, "likes_count": 0, "hashtags": [], "cashtags": [], "link": "https://twitter.com/usmanyusuf/status/1314201560100921347", "retweet": false, "quote_url": "", "video": 1, "thumbnail": "https://pbs.twimg.com/media/Ejz7V-0UwAIx5gg.jpg", "near": "", "geo": "9.083333333,7.533333,20km", "source": "", "user_rt_id": "", "user_rt": "", "retweet_id": "", "reply_to": [], "retweet_date": "", "translate": "", "trans_src": "", "trans_dest": ""}
{"id": 1314197720693911552, "conversation_id": "1314197692818452481", "created_at": "2020-10-08 15:35:27 CEST", "date": "2020-10-08", "time": "15:35:27", "timezone": "+0100", "user_id": 1141836619525345281, "username": "speakergbaja", "name": "Speaker of the House of Representatives", "place": "", "tweet": "On behalf of the Senate and House of Representatives of the Federal Republic of Nigeria, I extend sincere appreciation to His Excellency, President Muhammdu Buhari, GCFR for coming to the House today for this purpose, in fulfilment of the obligations of his office.  https://t.co/y0c3bOCjDS", "language": "en", "mentions": [], "urls": [], "photos": ["https://pbs.twimg.com/media/Ejz32y2VkAUpehS.jpg"], "replies_count": 1, "retweets_count": 24, "likes_count": 26, "hashtags": [], "cashtags": [], "link": "https://twitter.com/SpeakerGbaja/status/1314197720693911552", "retweet": false, "quote_url": "", "video": 1, "thumbnail": "https://pbs.twimg.com/media/Ejz32y2VkAUpehS.jpg", "near": "", "geo": "9.083333333,7.533333,20km", "source": "", "user_rt_id": "", "user_rt": "", "retweet_id": "", "reply_to": [], "retweet_date": "", "translate": "", "trans_src": "", "trans_dest": ""}
{"id": 1314188290715783170, "conversation_id": "1314188290715783170", "created_at": "2020-10-08 14:57:59 CEST", "date": "2020-10-08", "time": "14:57:59", "timezone": "+0100", "user_id": 471956864, "username": "cbngov_akin1", "name": "CBN Gov Akinsola Ak🇳🇬", "place": "", "tweet": "Breaking:   Buhari present's  N13 trillion 2021 budget", "language": "en", "mentions": [], "urls": [], "photos": [], "replies_count": 2, "retweets_count": 9, "likes_count": 46, "hashtags": [], "cashtags": [], "link": "https://twitter.com/cbngov_akin1/status/1314188290715783170", "retweet": false, "quote_url": "", "video": 0, "thumbnail": "", "near": "", "geo": "9.083333333,7.533333,20km", "source": "", "user_rt_id": "", "user_rt": "", "retweet_id": "", "reply_to": [], "retweet_date": "", "translate": "", "trans_src": "", "trans_dest": ""}
{"id": 1314187579034677249, "conversation_id": "1314187579034677249", "created_at": "2020-10-08 14:55:09 CEST", "date": "2020-10-08", "time": "14:55:09", "timezone": "+0100", "user_id": 842723117525094400, "username": "finminnigeria", "name": "Ministry of Finance, Budget and National Planning", "place": "", "tweet": "Hon. Ministers of @FinMinNigeria @PlanningNG, @ZShamsuna &amp; @ClemAgba as they arrived the National Assembly prior to President Muhammadu Buhari presenting the 2021 Budget Estimates to the joint session of @nassnigeria at the NASS Complex in Abuja.   #FGNBudget2021 #FinMinNigeria  https://t.co/F8Whd27MBS", "language": "en", "mentions": [{"screen_name": "finminnigeria", "name": "ministry of finance, budget and national planning", "id": "842723117525094400"}, {"screen_name": "planningng", "name": "budget & national planning ng", "id": "2506727486"}, {"screen_name": "zshamsuna", "name": "zainab shamsuna ahmed", "id": "1041925233744273408"}, {"screen_name": "clemagba", "name": "prince clem ikanade agba", "id": "1155598388236378112"}, {"screen_name": "nassnigeria", "name": "national assembly", "id": "2845191549"}], "urls": [], "photos": ["https://pbs.twimg.com/media/EjzuolBWkAUUUDj.jpg", "https://pbs.twimg.com/media/EjzuolGXcAAcDBX.jpg"], "replies_count": 20, "retweets_count": 36, "likes_count": 158, "hashtags": ["fgnbudget2021", "finminnigeria"], "cashtags": [], "link": "https://twitter.com/FinMinNigeria/status/1314187579034677249", "retweet": false, "quote_url": "", "video": 1, "thumbnail": "https://pbs.twimg.com/media/EjzuolBWkAUUUDj.jpg", "near": "", "geo": "9.083333333,7.533333,20km", "source": "", "user_rt_id": "", "user_rt": "", "retweet_id": "", "reply_to": [], "retweet_date": "", "translate": "", "trans_src": "", "trans_dest": ""}
{"id": 1314126908024598530, "conversation_id": "1314126908024598530", "created_at": "2020-10-08 10:54:04 CEST", "date": "2020-10-08", "time": "10:54:04", "timezone": "+0100", "user_id": 415803334, "username": "ahak2_", "name": "ahmad", "place": "", "tweet": "C’mon this can’t be happening under an incompetent  Buhari. Why?", "language": "en", "mentions": [], "urls": [], "photos": [], "replies_count": 0, "retweets_count": 0, "likes_count": 0, "hashtags": [], "cashtags": [], "link": "https://twitter.com/ahak2_/status/1314126908024598530", "retweet": false, "quote_url": "https://twitter.com/usmanyusuf/status/1313744725380300801", "video": 0, "thumbnail": "", "near": "", "geo": "9.083333333,7.533333,20km", "source": "", "user_rt_id": "", "user_rt": "", "retweet_id": "", "reply_to": [], "retweet_date": "", "translate": "", "trans_src": "", "trans_dest": ""}
{"id": 1314120135226150912, "conversation_id": "1314120135226150912", "created_at": "2020-10-08 10:27:10 CEST", "date": "2020-10-08", "time": "10:27:10", "timezone": "+0100", "user_id": 1060092587502133249, "username": "miz_arewa_nife", "name": "Miz Temmy 🌹🌹🌹", "place": "", "tweet": "Hope you all are following the #ESPMassHousing cause you need to do and understand some few things.  Under the Social Housing program of the ESP, there would also be Rent to Own option as part of the Buhari administration's resolve to enable the common man own his own home.", "language": "en", "mentions": [], "urls": [], "photos": [], "replies_count": 0, "retweets_count": 6, "likes_count": 4, "hashtags": ["espmasshousing"], "cashtags": [], "link": "https://twitter.com/miz_arewa_nife/status/1314120135226150912", "retweet": false, "quote_url": "", "video": 0, "thumbnail": "", "near": "", "geo": "9.083333333,7.533333,20km", "source": "", "user_rt_id": "", "user_rt": "", "retweet_id": "", "reply_to": [], "retweet_date": "", "translate": "", "trans_src": "", "trans_dest": ""}
{"id": 1314091303282638851, "conversation_id": "1314091303282638851", "created_at": "2020-10-08 08:32:35 CEST", "date": "2020-10-08", "time": "08:32:35", "timezone": "+0100", "user_id": 1060092587502133249, "username": "miz_arewa_nife", "name": "Miz Temmy 🌹🌹🌹", "place": "", "tweet": "#ESPMassHousing  Do you know that Buhari Government’s Mass Housing Programme Will Make 300,000 Poor Nigerians Landlords/Landladies Soon.  In June 2020, President Buhari approved the 2.3 Trillion Naira Economic Sustainability Plan (ESP) prepared by the Osinbajo-led  https://t.co/T7p5IQDZjB", "language": "en", "mentions": [], "urls": [], "photos": ["https://pbs.twimg.com/media/EjyXEjMWsAAxaP0.jpg"], "replies_count": 1, "retweets_count": 1, "likes_count": 1, "hashtags": ["espmasshousing"], "cashtags": [], "link": "https://twitter.com/miz_arewa_nife/status/1314091303282638851", "retweet": false, "quote_url": "", "video": 1, "thumbnail": "https://pbs.twimg.com/media/EjyXEjMWsAAxaP0.jpg", "near": "", "geo": "9.083333333,7.533333,20km", "source": "", "user_rt_id": "", "user_rt": "", "retweet_id": "", "reply_to": [], "retweet_date": "", "translate": "", "trans_src": "", "trans_dest": ""}
{"id": 1314086755994406914, "conversation_id": "1314086755994406914", "created_at": "2020-10-08 08:14:31 CEST", "date": "2020-10-08", "time": "08:14:31", "timezone": "+0100", "user_id": 1300671271592759296, "username": "bshivesocial", "name": "B’s Hive Hotel & Lounge 🎭", "place": "", "tweet": "It’s tomorrow guys 💕🎈! The Launch of B’s Hive Lounge! With 30% ✅off all drinks, BBQ, Shawama, Karaoke, guest artist and so much more !!! 🥰 Don’t miss this #tgif #AbujaTwitterCommunity #bshive #abuja #abj #Buhari #retweet #davido  https://t.co/OPuj4cCh85", "language": "en", "mentions": [], "urls": [], "photos": ["https://pbs.twimg.com/media/EjyS2_CWsAAQj1N.jpg"], "replies_count": 4, "retweets_count": 14, "likes_count": 10, "hashtags": ["tgif", "abujatwittercommunity", "bshive", "abuja", "abj", "buhari", "retweet", "davido"], "cashtags": [], "link": "https://twitter.com/BshiveSocial/status/1314086755994406914", "retweet": false, "quote_url": "", "video": 1, "thumbnail": "https://pbs.twimg.com/media/EjyS2_CWsAAQj1N.jpg", "near": "", "geo": "9.083333333,7.533333,20km", "source": "", "user_rt_id": "", "user_rt": "", "retweet_id": "", "reply_to": [], "retweet_date": "", "translate": "", "trans_src": "", "trans_dest": ""}
{"id": 1314077449169391616, "conversation_id": "1313770330482245632", "created_at": "2020-10-08 07:37:32 CEST", "date": "2020-10-08", "time": "07:37:32", "timezone": "+0100", "user_id": 136289683, "username": "spychief", "name": "General Shaba Baba Muhammad🔥", "place": "", "tweet": "@LawsBanks @AishaYesufu BREAKING President Buhari just approved Port Harcourt - Maiduguri Railway.  Hatred and hypocrisy will not let them see this", "language": "en", "mentions": [], "urls": [], "photos": [], "replies_count": 0, "retweets_count": 0, "likes_count": 0, "hashtags": [], "cashtags": [], "link": "https://twitter.com/spychief/status/1314077449169391616", "retweet": false, "quote_url": "", "video": 0, "thumbnail": "", "near": "", "geo": "9.083333333,7.533333,20km", "source": "", "user_rt_id": "", "user_rt": "", "retweet_id": "", "reply_to": [{"screen_name": "LawsBanks", "name": "Bankole", "id": "243332747"}, {"screen_name": "AishaYesufu", "name": "Aisha Yesufu", "id": "2531005222"}], "retweet_date": "", "translate": "", "trans_src": "", "trans_dest": ""}
